MANIFEST.in
README.rst
setup.py
grvlms_discovery.egg-info/PKG-INFO
grvlms_discovery.egg-info/SOURCES.txt
grvlms_discovery.egg-info/dependency_links.txt
grvlms_discovery.egg-info/entry_points.txt
grvlms_discovery.egg-info/requires.txt
grvlms_discovery.egg-info/top_level.txt
grvlmsdiscovery/__about__.py
grvlmsdiscovery/__init__.py
grvlmsdiscovery/plugin.py
grvlmsdiscovery/patches/https-create
grvlmsdiscovery/patches/k8s-deployments
grvlmsdiscovery/patches/k8s-deployments-nginx-init-containers
grvlmsdiscovery/patches/k8s-deployments-nginx-volume-mounts
grvlmsdiscovery/patches/k8s-deployments-nginx-volumes
grvlmsdiscovery/patches/k8s-ingress-rules
grvlmsdiscovery/patches/k8s-ingress-tls-hosts
grvlmsdiscovery/patches/k8s-jobs
grvlmsdiscovery/patches/k8s-services
grvlmsdiscovery/patches/kustomization-configmapgenerator
grvlmsdiscovery/patches/local-docker-compose-dev-services
grvlmsdiscovery/patches/local-docker-compose-nginx-volumes
grvlmsdiscovery/patches/local-docker-compose-services
grvlmsdiscovery/patches/nginx-extra
grvlmsdiscovery/patches/openedx-lms-common-settings
grvlmsdiscovery/templates/discovery/apps/settings/grvlms/__init__.py
grvlmsdiscovery/templates/discovery/apps/settings/grvlms/development.py
grvlmsdiscovery/templates/discovery/apps/settings/grvlms/production.py
grvlmsdiscovery/templates/discovery/apps/settings/partials/common.py
grvlmsdiscovery/templates/discovery/build/discovery/Dockerfile
grvlmsdiscovery/templates/discovery/build/discovery/assets.py
grvlmsdiscovery/templates/discovery/build/discovery/config.yml
grvlmsdiscovery/templates/discovery/hooks/discovery/init
grvlmsdiscovery/templates/discovery/hooks/lms/init
grvlmsdiscovery/templates/discovery/hooks/mysql/init